Workbook

Sheet Dashboard
A1: NEXORA | B1: Excel ERP Dashboard
A3: Gosterici | B3: Deyer | D3: Min stok siyahisi
A4: Umumi satis (AZN) | B4: =Reports!B4 -> 7061 | D4: sku | E4: name | F4: qty | G4: minStock
A5: Satis sayi | B5: =Reports!B5 -> 6 | D5: ELE-SONY-0003 | E5: Sony WH-1000XM5 Qulaqlıq | F5: 2 | G5: 5
A6: Orta cek (AZN) | B6: =Reports!B6 -> 1176.8333 | D6: FAS-RAYB-0007 | E6: Ray-Ban Meta Smart Eynək | F6: 1 | G6: 3
A7: Stok cemi | B7: =Reports!B10 -> 185
A8: Min stok alert | B8: =Reports!B11 -> 2
A9: Musteri sayi | B9: =COUNTA(Customers!A:A)-1 -> 5
A10: Techizatci | B10: =COUNTA(Suppliers!A:A)-1 -> 4
A11: Aciq senedler | B11: =COUNTIF(Documents!G:G,"active")+COUNTIF(Documents!G:G,"draft")+COUNTIF(Documents!G:G,"review") -> 4
A12: Gozleyen email | B12: =COUNTIF('Email Center'!G:G,"draft")+COUNTIF('Email Center'!G:G,"queued") -> 2
A14: Tez kecidler: Products | Inventory | Sales | Purchases | Documents | Email Center | Reports
A15: JSON sinxron: Products/Categories/Brands saheleri data/*.json ile eynidir.
A16: VBA: Auto SKU, sened nomreleme, Outlook - excel/vba/

Sheet Products
A1: id | B1: sku | C1: name | D1: brand | E1: category | F1: price | G1: oldPrice | H1: currency | I1: rating | J1: reviews | K1: badge | L1: inStock | M1: isNew | N1: minStock | O1: cost | P1: status
A2: p001 | B2: ELE-SAMS-0001 | C2: Samsung Galaxy S24 Ultra 256GB | D2: Samsung | E2: electronics | F2: 1899 | G2: 2199 | H2: ₼ | I2: 4.8 | J2: 124 | K2: Yeni | L2: TRUE | M2: TRUE | N2: 5 | O2: 1367.28 | P2: active
A3: p002 | B3: ELE-APPL-0002 | C3: Apple MacBook Pro 14" M3 Pro | D3: Apple | E3: electronics | F3: 3299 | H3: ₼ | I3: 4.9 | J3: 89 | L3: TRUE | M3: TRUE | N3: 3 | O3: 2375.28 | P3: active
A4: p003 | B4: ELE-SONY-0003 | C4: Sony WH-1000XM5 Qulaqlıq | D4: Sony | E4: electronics | F4: 449 | G4: 599 | H4: ₼ | I4: 4.7 | J4: 256 | K4: -25% | L4: TRUE | M4: TRUE | N4: 5 | O4: 323.28 | P4: active
A5: p004 | B5: HOM-DYSO-0004 | C5: Dyson V15 Detect Pəngvor | D5: Dyson | E5: home | F5: 899 | G5: 1099 | H5: ₼ | I5: 4.6 | J5: 67 | K5: Endirim | L5: TRUE | M5: TRUE | N5: 4 | O5: 647.28 | P5: active
A6: p005 | B6: FAS-NIKE-0005 | C6: Nike Air Max 90 Essential | D6: Nike | E6: fashion | F6: 189 | H6: ₼ | I6: 4.5 | J6: 312 | L6: TRUE | M6: TRUE | N6: 10 | O6: 136.08 | P6: active
A7: p006 | B7: ELE-LG-0006 | C7: LG OLED C4 55" 4K Smart TV | D7: LG | E7: electronics | F7: 2499 | G7: 2899 | H7: ₼ | I7: 4.8 | J7: 45 | K7: Top | L7: TRUE | M7: TRUE | N7: 2 | O7: 1799.28 | P7: active
A8: p007 | B8: FAS-RAYB-0007 | C8: Ray-Ban Meta Smart Eynək | D8: Ray-Ban | E8: fashion | F8: 549 | H8: ₼ | I8: 4.3 | J8: 28 | K8: Yeni | L8: TRUE | M8: TRUE | N8: 3 | O8: 395.28 | P8: active
A9: p008 | B9: ELE-SONY-0008 | C9: PlayStation 5 Slim + 2 Oyun | D9: Sony | E9: electronics | F9: 799 | G9: 899 | H9: ₼ | I9: 4.9 | J9: 178 | K9: Bundle | L9: TRUE | M9: TRUE | N9: 5 | O9: 575.28 | P9: active
A10: p009 | B10: HOM-XIAO-0009 | C10: Xiaomi Robot Vacuum S10+ | D10: Xiaomi | E10: home | F10: 599 | G10: 749 | H10: ₼ | I10: 4.4 | J10: 91 | K10: -20% | L10: TRUE | M10: FALSE | N10: 5 | O10: 431.28 | P10: active
A11: p010 | B11: SPO-ADID-0010 | C11: Adidas Ultraboost 22 | D11: Adidas | E11: sports | F11: 249 | G11: 299 | H11: ₼ | I11: 4.6 | J11: 203 | K11: Endirim | L11: TRUE | M11: FALSE | N11: 5 | O11: 179.28 | P11: active
A12: p011 | B12: HOM-PHIL-0011 | C12: Philips Hue Starter Kit | D12: Philips | E12: home | F12: 199 | H12: ₼ | I12: 4.5 | J12: 54 | L12: TRUE | M12: FALSE | N12: 5 | O12: 143.28 | P12: active
A13: p012 | B13: ELE-CANO-0012 | C13: Canon EOS R50 Mirrorless | D13: Canon | E13: electronics | F13: 1199 | G13: 1399 | H13: ₼ | I13: 4.7 | J13: 38 | K13: Yeni | L13: TRUE | M13: TRUE | N13: 5 | O13: 863.28 | P13: active
A14: p013 | B14: HOM-BOSC-0013 | C14: Bosch Serie 6 Qabyuyan | D14: Bosch | E14: home | F14: 1099 | H14: ₼ | I14: 4.6 | J14: 72 | L14: TRUE | M14: FALSE | N14: 5 | O14: 791.28 | P14: active
A15: p014 | B15: ELE-HUAW-0014 | C15: Huawei Watch GT 4 | D15: Huawei | E15: electronics | F15: 329 | G15: 399 | H15: ₼ | I15: 4.4 | J15: 116 | K15: -18% | L15: TRUE | M15: FALSE | N15: 5 | O15: 236.88 | P15: active
A16: p015 | B16: SPO-NIKE-0015 | C16: Nike Dri-FIT Training T-Shirt | D16: Nike | E16: sports | F16: 59 | G16: 79 | H16: ₼ | I16: 4.3 | J16: 188 | K16: Endirim | L16: TRUE | M16: FALSE | N16: 5 | O16: 42.48 | P16: active
A17: p016 | B17: KID-LEGO-0016 | C17: LEGO Technic Bugatti | D17: LEGO | E17: kids | F17: 449 | H17: ₼ | I17: 4.9 | J17: 64 | K17: Top | L17: FALSE | M17: FALSE | N17: 5 | O17: 323.28 | P17: active

Sheet Categories
A1: id | B1: name | C1: slug | D1: count | E1: icon | F1: status
A2: electronics | B2: Elektronika | C2: elektronika | D2: 1240 | E2: smartphone | F2: active
A3: fashion | B3: Moda | C3: moda | D3: 856 | E3: shirt | F3: active
A4: home | B4: Ev & Bağça | C4: ev-bagca | D4: 634 | E4: home | F4: active
A5: beauty | B5: Gözəllik | C5: gozellik | D5: 412 | E5: sparkles | F5: active
A6: sports | B6: İdman | C6: idman | D6: 298 | E6: dumbbell | F6: active
A7: kids | B7: Uşaq | C7: usaq | D7: 367 | E7: baby | F7: active
A8: auto | B8: Avtomobil | C8: avtomobil | D8: 189 | E8: car | F8: active
A9: books | B9: Kitab & Hobi | C9: kitab-hobi | D9: 523 | E9: book | F9: active

Sheet Brands
A1: id | B1: name | C1: logo | D1: color | E1: status
A2: samsung | B2: Samsung | C2: S | D2: #1428A0 | E2: active
A3: apple | B3: Apple | D3: #000000 | E3: active
A4: sony | B4: Sony | C4: SONY | D4: #000000 | E4: active
A5: lg | B5: LG | C5: LG | D5: #A50034 | E5: active
A6: nike | B6: Nike | C6: ✓ | D6: #111111 | E6: active
A7: adidas | B7: Adidas | C7: Adi | D7: #000000 | E7: active
A8: dyson | B8: Dyson | C8: DYSON | D8: #C4398A | E8: active
A9: philips | B9: Philips | C9: PHILIPS | D9: #0E5FD8 | E9: active
A10: bosch | B10: Bosch | C10: BOSCH | D10: #EA0016 | E10: active
A11: xiaomi | B11: Xiaomi | C11: mi | D11: #FF6700 | E11: active
A12: huawei | B12: Huawei | C12: HUAWEI | D12: #CF0A2C | E12: active
A13: canon | B13: Canon | C13: Canon | D13: #BC0024 | E13: active
A14: rayban | B14: Ray-Ban | C14: RB | D14: #111111 | E14: active
A15: lego | B15: LEGO | C15: LEGO | D15: #E3000B | E15: active
A16: ray-ban | B16: Ray-Ban | C16: RB | D16: #111111 | E16: active

Sheet Inventory
A1: id | B1: sku | C1: name | D1: warehouse | E1: location | F1: qty | G1: minStock | H1: reorderQty | I1: status | J1: alert
A2: p001 | B2: ELE-SAMS-0001 | C2: Samsung Galaxy S24 Ultra 256GB | D2: WH-BAK-01 | E2: A-12 | F2: 24 | G2: 5 | H2: 10 | I2: ok | J2: =IF(F2<=G2,"MIN STOK","OK") -> OK
A3: p002 | B3: ELE-APPL-0002 | C3: Apple MacBook Pro 14" M3 Pro | D3: WH-BAK-01 | E3: A-03 | F3: 8 | G3: 3 | H3: 10 | I3: ok | J3: =IF(F3<=G3,"MIN STOK","OK") -> OK
A4: p003 | B4: ELE-SONY-0003 | C4: Sony WH-1000XM5 Qulaqlıq | D4: WH-BAK-02 | E4: B-08 | F4: 2 | G4: 5 | H4: 10 | I4: low | J4: =IF(F4<=G4,"MIN STOK","OK") -> MIN STOK
A5: p004 | B5: HOM-DYSO-0004 | C5: Dyson V15 Detect Pəngvor | D5: WH-BAK-02 | E5: C-01 | F5: 15 | G5: 4 | H5: 10 | I5: ok | J5: =IF(F5<=G5,"MIN STOK","OK") -> OK
A6: p005 | B6: FAS-NIKE-0005 | C6: Nike Air Max 90 Essential | D6: WH-GAN-01 | E6: D-04 | F6: 40 | G6: 10 | H6: 20 | I6: ok | J6: =IF(F6<=G6,"MIN STOK","OK") -> OK
A7: p006 | B7: ELE-LG-0006 | C7: LG OLED C4 55" 4K Smart TV | D7: WH-BAK-01 | E7: A-20 | F7: 3 | G7: 2 | H7: 10 | I7: ok | J7: =IF(F7<=G7,"MIN STOK","OK") -> OK
A8: p007 | B8: FAS-RAYB-0007 | C8: Ray-Ban Meta Smart Eynək | D8: WH-BAK-02 | E8: B-02 | F8: 1 | G8: 3 | H8: 10 | I8: low | J8: =IF(F8<=G8,"MIN STOK","OK") -> MIN STOK
A9: p008 | B9: ELE-SONY-0008 | C9: PlayStation 5 Slim + 2 Oyun | D9: WH-BAK-01 | E9: A-15 | F9: 12 | G9: 5 | H9: 10 | I9: ok | J9: =IF(F9<=G9,"MIN STOK","OK") -> OK
A10: p009 | B10: HOM-XIAO-0009 | C10: Xiaomi Robot Vacuum S10+ | D10: WH-BAK-01 | E10: Z-01 | F10: 10 | G10: 5 | H10: 10 | I10: ok | J10: =IF(F10<=G10,"MIN STOK","OK") -> OK
A11: p010 | B11: SPO-ADID-0010 | C11: Adidas Ultraboost 22 | D11: WH-BAK-01 | E11: Z-01 | F11: 10 | G11: 5 | H11: 10 | I11: ok | J11: =IF(F11<=G11,"MIN STOK","OK") -> OK
A12: p011 | B12: HOM-PHIL-0011 | C12: Philips Hue Starter Kit | D12: WH-BAK-01 | E12: Z-01 | F12: 10 | G12: 5 | H12: 10 | I12: ok | J12: =IF(F12<=G12,"MIN STOK","OK") -> OK
A13: p012 | B13: ELE-CANO-0012 | C13: Canon EOS R50 Mirrorless | D13: WH-BAK-01 | E13: Z-01 | F13: 10 | G13: 5 | H13: 10 | I13: ok | J13: =IF(F13<=G13,"MIN STOK","OK") -> OK
... A17: p016 | B17: KID-LEGO-0016 | C17: LEGO Technic Bugatti | D17: WH-BAK-01 | E17: Z-01 | F17: 10 | G17: 5 | H17: 10 | I17: ok | J17: =IF(F17<=G17,"MIN STOK","OK") -> OK

Sheet Purchases
A1: poNo | B1: date | C1: supplierId | D1: supplierName | E1: productId | F1: sku | G1: qty | H1: unitCost | I1: total | J1: status | K1: notes
A2: PO-2026-0001 | B2: 46204 | C2: s001 | D2: Tech Distrib LLC | E2: p001 | F2: ELE-SAMS-0001 | G2: 20 | H2: 1350 | I2: =G2*H2 -> 27000 | J2: received | K2: Samsung stok
A3: PO-2026-0002 | B3: 46208 | C3: s004 | D3: Global Gadgets | E3: p003 | F3: ELE-SONY-0003 | G3: 30 | H3: 300 | I3: =G3*H3 -> 9000 | J3: received | K3: Qulaqliq
A4: PO-2026-0003 | B4: 46215 | C4: s002 | D4: Fashion Hub | E4: p005 | F4: FAS-NIKE-0005 | G4: 50 | H4: 110 | I4: =G4*H4 -> 5500 | J4: ordered | K4: Nike partiya
A5: PO-2026-0004 | B5: 46223 | C5: s003 | D5: Home Supplies AZ | E5: p004 | F5: HOM-DYSO-0004 | G5: 10 | H5: 620 | I5: =G5*H5 -> 6200 | J5: partial | K5: Dyson
A6: PO-2026-0005 | B6: 46231 | C6: s001 | D6: Tech Distrib LLC | E6: p008 | F6: ELE-SONY-0008 | G6: 15 | H6: 560 | I6: =G6*H6 -> 8400 | J6: ordered | K6: PS5

Sheet Sales
A1: soNo | B1: date | C1: customerId | D1: customerName | E1: productId | F1: sku | G1: qty | H1: unitPrice | I1: discount | J1: total | K1: channel | L1: status
A2: SO-2026-0001 | B2: 46206 | C2: c001 | D2: Reshad Memmedov | E2: p001 | F2: ELE-SAMS-0001 | G2: 1 | H2: 1899 | I2: 0 | J2: =G2*H2-I2 -> 1899 | K2: web | L2: paid
A3: SO-2026-0002 | B3: 46211 | C3: c002 | D3: Leyla Hesenova | E3: p003 | F3: ELE-SONY-0003 | G3: 2 | H3: 449 | I3: 50 | J3: =G3*H3-I3 -> 848 | K3: web | L3: paid
A4: SO-2026-0003 | B4: 46218 | C4: c004 | D4: Nigar Eliyeva | E4: p006 | F4: ELE-LG-0006 | G4: 1 | H4: 2499 | I4: 100 | J4: =G4*H4-I4 -> 2399 | K4: b2b | L4: paid
A5: SO-2026-0004 | B5: 46225 | C5: c003 | D5: Elvin Quliyev | E5: p005 | F5: FAS-NIKE-0005 | G5: 3 | H5: 189 | I5: 0 | J5: =G5*H5-I5 -> 567 | K5: web | L5: shipped
A6: SO-2026-0005 | B6: 46228 | C6: c001 | D6: Reshad Memmedov | E6: p008 | F6: ELE-SONY-0008 | G6: 1 | H6: 799 | I6: 0 | J6: =G6*H6-I6 -> 799 | K6: web | L6: paid
A7: SO-2026-0006 | B7: 46233 | C7: c002 | D7: Leyla Hesenova | E7: p007 | F7: FAS-RAYB-0007 | G7: 1 | H7: 549 | I7: 0 | J7: =G7*H7-I7 -> 549 | K7: web | L7: pending

Sheet Customers
A1: id | B1: name | C1: email | D1: phone | E1: company | F1: city | G1: address | H1: type | I1: status
A2: c001 | B2: Reshad Memmedov | C2: reshad@example.az | D2: 994501112233 | E2: RM Tech | F2: Baki | G2: Nizami 12 | H2: retail | I2: active
A3: c002 | B3: Leyla Hesenova | C3: leyla@example.az | D3: 994552223344 | E3: LH Design | F3: Gence | G3: Ataturk 45 | H3: wholesale | I3: active
A4: c003 | B4: Elvin Quliyev | C4: elvin@example.az | D4: 994703334455 | E4: EQ Trade | F4: Sumqayit | G4: 39596 | H4: retail | I4: active
A5: c004 | B5: Nigar Eliyeva | C5: nigar@example.az | D5: 994554445566 | E5: Nexora B2B | F5: Baki | G5: Heyder Eliyev 120 | H5: corporate | I5: active
A6: c005 | B6: Tural Ismayilov | C6: tural@example.az | D6: 994505556677 | E6: TI Market | F6: Mingechevir | G6: Merkez 3 | H6: retail | I6: inactive

Sheet Suppliers
A1: id | B1: name | C1: email | D1: phone | E1: city | F1: category | G1: paymentTerms | H1: status
A2: s001 | B2: Tech Distrib LLC | C2: sales@techdistrib.az | D2: 994125551100 | E2: Baki | F2: electronics | G2: Net 30 | H2: active
A3: s002 | B3: Fashion Hub | C3: order@fashionhub.az | D3: 994125552200 | E3: Baki | F3: fashion | G3: Net 15 | H3: active
A4: s003 | B4: Home Supplies AZ | C4: info@homesup.az | D4: 994125553300 | E4: Sumqayit | F4: home | G4: Net 45 | H4: active
A5: s004 | B5: Global Gadgets | C5: baku@globalgadgets.com | D5: 994125554400 | E5: Baki | F5: electronics | G5: Prepaid | H5: active

Sheet Documents
A1: docNo | B1: docType | C1: title | D1: relatedTo | E1: party | F1: date | G1: status | H1: templateFile | I1: archivePath | J1: notes
A2: DOC-2026-0001 | B2: invoice | C2: Satis hesab-faktura | D2: SO-2026-0001 | E2: Reshad Memmedov | F2: 46206 | G2: archived | H2: 01-hesab-faktura.html | I2: Archive | J2: Odenilib
A3: DOC-2026-0002 | B3: delivery | C3: Catdirilma qebzi | D3: SO-2026-0002 | E3: Leyla Hesenova | F3: 46212 | G3: active | H3: 03-catdirilma-qebzi.html
A4: DOC-2026-0003 | B4: purchase | C4: Alis sifarisi | D4: PO-2026-0003 | E4: Fashion Hub | F4: 46215 | G4: active | H4: 10-alis-sifarisi.html
A5: DOC-2026-0004 | B5: contract | C5: B2B muqavile | D5: c004 | E5: Nexora B2B | F5: 46218 | G5: review | H5: 15-b2b-muqavile.html
A6: DOC-2026-0005 | B6: return | C6: Qaytarma akti | D6: SO-2026-0004 | E6: Elvin Quliyev | F6: 46229 | G6: draft | H6: 07-qaytarma-akti.html
A12: Sened novleri (sablon kataloqu) - 42 sablon
A13: code | B13: ad | C13: templateFile | D13: prefix
A14: invoice | B14: Hesab-faktura | C14: 01-hesab-faktura.html | D14: INV
A15: proforma | B15: Proforma faktura | C15: 02-proforma.html | D15: PRF
A16: delivery | B16: Catdirilma qebzi | C16: 03-catdirilma-qebzi.html | D16: DLV
A17: packing | B17: Qablasdirma siyahisi | C17: 04-qablasdirma.html | D17: PKG
A18: quote | B18: Qiymet teklifi | C18: 05-qiymet-teklifi.html | D18: QTE
A19: order | B19: Satis sifarisi | C19: 06-satis-sifarisi.html | D19: ORD
A20: return | B20: Qaytarma akti | C20: 07-qaytarma-akti.html | D20: RTN
A21: credit | B21: Kredit notasi | C21: 08-kredit-nota.html | D21: CRN
A22: debit | B22: Debet notasi | C22: 09-debet-nota.html | D22: DBN
A23: purchase | B23: Alis sifarisi | C23: 10-alis-sifarisi.html | D23: PO
A24: grn | B24: Mal qebulu | C24: 11-mal-qebulu.html | D24: GRN
... A55: handover | B55: Tehvil-teslim | C55: 42-tehvil-teslim.html | D55: HND

Sheet Email Center
A1: emailNo | B1: template | C1: customerId | D1: customerName | E1: toEmail | F1: subject | G1: status | H1: created | I1: sentAt | J1: mailto
A2: EM-2026-0001 | B2: order-confirm | C2: c001 | D2: Reshad Memmedov | E2: reshad@example.az | F2: NEXORA - Sifaris tesdiqi SO-2026-0001 | G2: sent | H2: 46206 | I2: 46206 | J2: =HYPERLINK("mailto:"&E2&"?subject="&F2,"mailto ac") -> mailto ac
A3: EM-2026-0002 | B3: shipping | C3: c002 | D3: Leyla Hesenova | E3: leyla@example.az | F3: NEXORA - Sifarisiniz yoldadir | G3: sent | H3: 46212 | I3: 46212 | J3: =HYPERLINK("mailto:"&E3&"?subject="&F3,"mailto ac") -> mailto ac
A4: EM-2026-0003 | B4: promo | C4: c004 | D4: Nigar Eliyeva | E4: nigar@example.az | F4: NEXORA - Yay kampaniyasi | G4: draft | H4: 46223 | J4: =HYPERLINK("mailto:"&E4&"?subject="&F4,"mailto ac") -> mailto ac
A5: EM-2026-0004 | B5: low-stock-internal | D5: Anbar komandasi | E5: stock@nexora.az | F5: Min stok xeberdarligi | G5: queued | H5: 46231 | J5: =HYPERLINK("mailto:"&E5&"?subject="&F5,"mailto ac") -> mailto ac
A8: Email sablonlari | F8: Musteri sec (id) | G8: c001
A9: code | B9: ad | C9: fayl | D9: deyisenler | F9: Ad | G9: =IFERROR(VLOOKUP(G8,Customers!A:B,2,FALSE),"") -> Reshad Memmedov
A10: order-confirm | B10: Sifaris tesdiqi | C10: email-order-confirm.html | D10: {{name}},{{soNo}},{{total}} | F10: Email | G10: =IFERROR(VLOOKUP(G8,Customers!A:C,3,FALSE),"") -> reshad@example.az
A11: shipping | B11: Catdirilma izleme | C11: email-shipping.html | D11: {{name}},{{tracking}},{{soNo}}
A12: delivered | B12: Catdirildi | C12: email-delivered.html | D12: {{name}},{{soNo}}
A13: promo | B13: Kampaniya | C13: email-promo.html | D13: {{name}},{{promoCode}},{{ends}}
A14: welcome | B14: Xos geldiniz | C14: email-welcome.html | D14: {{name}}
A15: password-reset | B15: Sifre sifirlama | C15: email-password-reset.html | D15: {{name}},{{resetLink}}
A16: abandoned-cart | B16: Sebet xatirlatma | C16: email-abandoned-cart.html | D16: {{name}},{{cartTotal}}
A17: review-request | B17: Rey sorgusu | C17: email-review-request.html | D17: {{name}},{{product}}
A18: refund | B18: Geri odenis | C18: email-refund.html | D18: {{name}},{{amount}},{{soNo}}
A19: b2b-quote | B19: B2B teklif | C19: email-b2b-quote.html | D19: {{company}},{{quoteNo}}
A20: low-stock-internal | B20: Min stok (daxili) | C20: email-low-stock.html | D20: {{sku}},{{qty}},{{minStock}}
A21: newsletter | B21: Bulleten | C21: email-newsletter.html | D21: {{name}},{{month}}

Sheet Reports
A1: NEXORA - HESABATLAR
A3: Satis xulasesi
A4: Umumi satis meblegi | B4: =SUM(Sales!J:J) -> 7061
A5: Satis sayi | B5: =COUNTA(Sales!A:A)-1 -> 6
A6: Orta cek | B6: =IFERROR(B4/B5,0) -> 1176.8333
A7: Odenilmis satislar | B7: =COUNTIF(Sales!L:L,"paid") -> 4
A9: Stok xulasesi
A10: Umumi miqdar | B10: =SUM(Inventory!F:F) -> 185
A11: Min stok xeberdarligi | B11: =COUNTIF(Inventory!J:J,"MIN STOK") -> 2
A12: Mehsul sayi | B12: =COUNTA(Products!A:A)-1 -> 16
A14: Alis xulasesi
A15: Alis cemi | B15: =SUM(Purchases!I:I) -> 56100
A16: Aciq PO | B16: =COUNTIF(Purchases!J:J,"ordered")+COUNTIF(Purchases!J:J,"partial") -> 3
A18: Kateqoriya uzre katalog qiymet cemi
A19: category | B19: catalogPriceSum
A20: electronics | B20: =SUMIF(Products!E:E,"electronics",Products!F:F) -> 10473
A21: fashion | B21: =SUMIF(Products!E:E,"fashion",Products!F:F) -> 738
A22: home | B22: =SUMIF(Products!E:E,"home",Products!F:F) -> 2796
A24: Qeyd: Tam PivotTable uchun Sales+Products -> Insert -> PivotTable (bax excel/README.md).

Sheet Settings
A1: NEXORA ERP - PARAMETRLER
A3: Acar | B3: Deyer
A4: Sirket adi | B4: NEXORA
A5: Valyuta | B5: AZN
A6: Valyuta simvolu | B6: AZN
A7: EDV % | B7: 18
A8: SKU prefiks | B8: NX
A9: SKU ayirici | B9: -
A10: Sened prefiks | B10: DOC
A11: Satis prefiks | B11: SO
A12: Alis prefiks | B12: PO
A13: Email prefiks | B13: EM
A14: Min stok rengi | B14: Qirmizi
A15: Anbar esas | B15: WH-BAK-01
A16: JSON export qovlugu | B16: ..\data\
A17: Son sinxron | B17: 46236.216
A18: VBA AutoSKU | B18: Aktiv (bax: vba/)
A19: Outlook inteqrasiya | B19: mailto + VBA COM
A22: Web JSON uygunluq
A23: Products: id, name, brand, category, price, oldPrice, currency, inStock
A24: Categories: id, name, slug
A25: Brands: id, name

Sheet Archive
A1: archiveId | B1: source | C1: refNo | D1: title | E1: archivedAt | F1: path | G1: tags
A2: ARC-0001 | B2: Documents | C2: DOC-2026-0001 | D2: Satis hesab-faktura | E2: 46213 | F2: Archive/2026/07/ | G2: invoice,paid
A3: ARC-0002 | B3: Sales | C3: SO-2026-0001 | D3: Satis baglandi | E3: 46213 | F3: Archive/2026/07/ | G3: sales
A4: ARC-0003 | B4: Email Center | C4: EM-2026-0001 | D4: Gonderilmis email | E4: 46206 | F4: Archive/email/ | G4: email
